whitespacelint/__init__.py
whitespacelint/whitespacelint.py
whitespacelint-1.1.0.dist-info/LICENSE
whitespacelint-1.1.0.dist-info/METADATA
whitespacelint-1.1.0.dist-info/WHEEL
whitespacelint-1.1.0.dist-info/entry_points.txt
whitespacelint-1.1.0.dist-info/top_level.txt
whitespacelint-1.1.0.dist-info/RECORD
